pywood/__init__.py
pywood/_conversation.py
pywood/_exceptions.py
pywood/_utils.py
pywood/context.py
pywood/decorators.py
pywood/devtools.py
pywood/errors.py
pywood/eventlib.py
pywood/events.py
pywood/pooling.py
pywood/providers.py
pywood/states.py
pywood/updates/__init__.py
pywood/updates/callbacks.py
pywood/updates/commands.py
pywood/updates/generate.py
pywood/updates/numbers.py
pywood/updates/photos.py
pywood/updates/texts.py
pywood/updates/utils.py
tests/__init__.py
tests/test_conversation.py
tests/test_states.py
tests/test_utils.py
tests/test_decorators/__init__.py
tests/test_decorators/test_decorator_event.py
tests/test_decorators/test_decorator_events.py
tests/test_decorators/test_decorator_no_events.py
tests/test_decorators/test_together.py
tests/test_updates/__init__.py
tests/test_updates/test_callbacks.py
tests/test_updates/test_commands.py
tests/test_updates/test_generate.py
tests/test_updates/test_numbers.py
tests/test_updates/test_photos.py
tests/test_updates/test_texts.py
tests/test_updates/test_utils.py
pywood-0.1.3.dist-info/AUTHORS.rst
pywood-0.1.3.dist-info/LICENSE
pywood-0.1.3.dist-info/METADATA
pywood-0.1.3.dist-info/WHEEL
pywood-0.1.3.dist-info/top_level.txt
pywood-0.1.3.dist-info/RECORD
