Metadata-Version: 2.1
Name: pywood
Version: 0.1.3
Summary: Lightweight framework to build Telegram bots.
Home-page: https://github.com/pynista/pywood
Author: Dzmitry Maliuzhenets
Author-email: dzmitrymaliuzhenets@gmail.com
License: UNKNOWN
Keywords: telegram api bot framework durov
Platform: UNKNOWN
Classifier: Development Status :: 2 - Pre-Alpha
Classifier: Intended Audience :: Developers
Classifier: Natural Language :: English
Classifier: Natural Language :: Russian
Classifier: License :: OSI Approved :: MIT License
Classifier: Programming Language :: Python :: 3.7
Classifier: Programming Language :: Python :: Implementation :: CPython
Classifier: Operating System :: OS Independent
Requires-Python: ~=3.7
Requires-Dist: prettyprinter
Requires-Dist: wheel
Requires-Dist: telegrambotapiwrapper
